rtl/alu/full_adder.sv
`timescale 1ns/1ps

module full_adder (
  input logic A, B, Cin,
  output logic S, C
);
  logic w1, w2, w3;

  xor G1 (w1, A, B);
  xor G2 (S, w1, Cin);

  and G3 (w2, Cin, w1);
  and G4 (w3, A, B);

  or  G5 (C, w2, w3);
endmodule

tb/full_adder_tb.sv
`timescale 1ns/1ps

module full_adder_tb;
  logic a, b, cin;
  logic s, c;

  full_adder uut (
    .A(a),
    .B(b),
    .Cin(cin),
    .S(s),
    .C(c)
    );

  initial begin
    $dumpfile("full_adder.vcd");
    $dumpvars(0, full_adder_tb);

    $display("Time\t A B Cin | S C");
    $monitor("%g\t %b %b  %b  | %b %b", $time, a, b, cin, s, c);

    {a, b, cin} = 3'b000; #10;
    {a, b, cin} = 3'b001; #10;
    {a, b, cin} = 3'b010; #10;
    {a, b, cin} = 3'b011; #10;
    {a, b, cin} = 3'b100; #10;
    {a, b, cin} = 3'b101; #10;
    {a, b, cin} = 3'b110; #10;
    {a, b, cin} = 3'b111; #10;

    $display("Verification Complete.");
    $finish;
  end
endmodule

full_adder.vcd
$version Generated by VerilatedVcd $end
$timescale 1ps $end
 $scope module full_adder_tb $end
  $var wire 1 " a $end
  $var wire 1 # b $end
  $var wire 1 $ cin $end
  $var wire 1 % s $end
  $var wire 1 & c $end
  $scope module uut $end
   $var wire 1 " A $end
   $var wire 1 # B $end
   $var wire 1 $ Cin $end
   $var wire 1 % S $end
   $var wire 1 & C $end
   $var wire 1 ' w1 $end
   $var wire 1 ( w2 $end
   $var wire 1 ) w3 $end
  $upscope $end
 $upscope $end
$enddefinitions $end


#0
0"
0#
0$
0%
0&
0'
0(
0)
#10000
1$
1%
#20000
1#
0$
1'
#30000
1$
0%
1&
1(
#40000
1"
0#
0$
1%
0&
0(
#50000
1$
0%
1&
1(
#60000
1#
0$
0'
0(
1)
#70000
1$
1%
